{"config":{"codepayalipay":{"id":"2","payment":"\u7801\u652f\u4ed8-\u652f\u4ed8\u5b9d\u626b\u7801\u652f\u4ed8","payname":"\u652f\u4ed8\u5b9d","payimage":"\/res\/images\/pay\/alipay.jpg","alias":"codepayalipay","sign_type":"RSA2","app_id":"15272","app_secret":"1mnj0B5aZL5Cio8Xnd9f8kjnCpDika","ali_public_key":"","rsa_private_key":"","configure3":"","overtime":"300","active":"1"},"codepayqq":{"id":"3","payment":"\u7801\u652f\u4ed8-QQ\u626b\u7801\u652f\u4ed8","payname":"\u624b\u673aQQ","payimage":"\/res\/images\/pay\/qqpay.jpg","alias":"codepayqq","sign_type":"RSA2","app_id":"15272","app_secret":"1mnj0B5aZL5Cio8Xnd9f8kjnCpDika","ali_public_key":"","rsa_private_key":"","configure3":"","overtime":"300","active":"1"},"codepaywx":{"id":"4","payment":"\u7801\u652f\u4ed8-\u5fae\u4fe1\u626b\u7801\u652f\u4ed8","payname":"\u5fae\u4fe1","payimage":"\/res\/images\/pay\/weixin.jpg","alias":"codepaywx","sign_type":"RSA2","app_id":"15272","app_secret":"1mnj0B5aZL5Cio8Xnd9f8kjnCpDika","ali_public_key":"","rsa_private_key":"","configure3":"","overtime":"300","active":"1"}},"expire_time":1546949217}